couchdb_storage/CouchDBStorage.py
couchdb_storage/__init__.py
django_couchdb_storage-0.0.2.dist-info/LICENSE
django_couchdb_storage-0.0.2.dist-info/METADATA
django_couchdb_storage-0.0.2.dist-info/WHEEL
django_couchdb_storage-0.0.2.dist-info/top_level.txt
django_couchdb_storage-0.0.2.dist-info/RECORD
