Metadata-Version: 2.1
Name: django-couchdb-storage
Version: 0.0.2
Summary: Django storage backend for CouchDB
Home-page: https://github.com/5in4/django-couchdb-storage
Author: Dominik Seemann
Author-email: dominik@seemann.rocks
License: UNKNOWN
Platform: UNKNOWN
Classifier: Programming Language :: Python :: 3
Classifier: License :: OSI Approved :: MIT License
Classifier: Operating System :: OS Independent
Requires-Dist: requests (>=2.0)
